Workbook

Sheet 00_Read Me
A1: Pakistan Economic Outlook & Market Analysis
A3: Project purpose
A4: Professional economics + finance research project covering Pakistan's growth, inflation, monetary policy, currency, external sector and KSE-100 performance.
A7: Period | B7: 2010–2025 calendar-year dataset
A8: Core question | B8: How have Pakistan's macroeconomic conditions and financial-market performance moved together?
A9: Tools | B9: Microsoft Excel; structured so the cleaned data can also feed Power BI later
A10: Main outputs | B10: Economic trends, external-sector analysis, monetary/currency analysis, KSE-100 analysis and correlations
A11: Methodology | B11: World Bank macro indicators use calendar-year data; KSE-100 uses calendar-year closing levels.
A12: Policy-rate note | B12: Standardized SBP Policy (Target) Rate is used from 2015 onward. 2010–2014 are marked N/A rather than mixing different interest-rate definitions.
A15: Workbook structure
A16: 01_Sources | B16: Source register, indicator definitions, coverage and URLs
A17: 02_Raw Data | B17: Clean historical research dataset
A18: 03_Calculations | B18: Derived indicators: FX depreciation, trade balance and approximate real policy rate
A19: 04_Correlation | B19: Correlation matrix for core economic/market variables
A20: 05_Economic Analysis | B20: Economic summary tables and charts
A21: 06_Market Analysis | B21: KSE-100 analysis and macro-market comparison
A24: Quality control
A25: No forecast values are mixed into the historical dataset. Where a standardized series starts later, the workbook explicitly marks the unavailable years.

Sheet 01_Sources
A1: Source ID | B1: Institution / Source | C1: Indicator(s) | D1: Coverage / Use | E1: URL | F1: Notes
A2: S01 | B2: World Bank – World Development Indicators | C2: GDP growth; CPI inflation; exports % GDP; imports % GDP; remittances % GDP; current account % GDP; official exchange rate | D2: 2010–2025 | E2: https://data.worldbank.org/country/pakistan | F2: Primary macro dataset; CC BY 4.0.
A3: S02 | B3: World Bank – GDP Growth | C3: GDP growth (annual %) | D3: 2010–2025 | E3: https://data.worldbank.org/indicator/NY.GDP.MKTP.KD.ZG?locations=PK | F3: Calendar-year WDI series.
A4: S03 | B4: World Bank – CPI Inflation | C4: Inflation, consumer prices (annual %) | D4: 2010–2025 | E4: https://data.worldbank.org/indicator/FP.CPI.TOTL.ZG?locations=PK | F4: Calendar-year WDI series.
A5: S04 | B5: World Bank – Exchange Rate | C5: Official exchange rate, LCU per US$, period average | D5: 2010–2025 | E5: https://data.worldbank.org/indicator/PA.NUS.FCRF?locations=PK | F5: Annual average; underlying source is IMF International Financial Statistics.
A6: S05 | B6: World Bank – External Sector | C6: Exports/imports % GDP; current account % GDP; remittances % GDP | D6: 2010–2025 where available | E6: https://data.worldbank.org/country/pakistan | F6: World Bank WDI indicators; some underlying series are IMF BOP data.
A7: S06 | B7: State Bank of Pakistan – EasyData / Monetary Policy | C7: Policy (Target) Rate | D7: 2015–2025 | E7: https://easydata.sbp.org.pk/ | F7: Year-end policy target rate used for this project.
A8: S07 | B8: Pakistan Stock Exchange | C8: KSE-100 definition and recent official values | D8: 2021–2025 cross-check | E8: https://www.psx.com.pk/psx/product-and-services/indices | F8: KSE-100 is the major free-float market-capitalization index.
A9: S08 | B9: KSE-100 historical annual performance | C9: Calendar-year KSE-100 closes/returns | D9: 2010–2025 | E9: https://en.wikipedia.org/wiki/KSE_100_Index | F9: Used for a consistent calendar-year close/return series; recent observations cross-checked against PSX.

Sheet 02_Raw Data
A1: Year | B1: GDP Growth (%) | C1: CPI Inflation (%) | D1: Policy Rate EOP (%) | E1: USD/PKR Avg | F1: Exports (% GDP) | G1: Imports (% GDP) | H1: Remittances (% GDP) | I1: Current Account (% GDP) | J1: KSE-100 Close | K1: KSE-100 Return (%)
A2: 2010 | B2: 1.5 | C2: 12.9389 | E2: 85.19 | F2: 12.64 | G2: 19.35 | H2: 4.926 | I2: -0.7 | J2: 12022.46
A3: 2011 | B3: 2.68 | C3: 11.9161 | E3: 86.34 | F3: 13.48 | G3: 18.88 | H3: 5.3182 | I3: -1 | J3: 11347.66 | K3: -5.612828
A4: 2012 | B4: 3.03 | C4: 9.6824 | E4: 93.4 | F4: 11.87 | G4: 19.45 | H4: 5.6004 | I4: -0.9 | J4: 16905.33 | K4: 48.976353
A5: 2013 | B5: 4.37 | C5: 7.6922 | E5: 101.63 | F5: 12.18 | G5: 18.71 | H5: 5.6557 | I5: -1.7 | J5: 25261.14 | K5: 49.427074
A6: 2014 | B6: 4.12 | C6: 7.1894 | D6: 6.5 | E6: 101.1 | F6: 11.19 | G6: 18.27 | H6: 6.3539 | I6: -1.3 | J6: 32131.28 | K6: 27.196476
A7: 2015 | B7: 4.22 | C7: 2.5293 | D7: 5.75 | E7: 102.77 | F7: 9.97 | G7: 16.71 | H7: 6.4361 | I7: -0.9 | J7: 32816.31 | K7: 2.1319723
A8: 2016 | B8: 6.57 | C8: 3.7651 | D8: 6 | E8: 104.77 | F8: 8.74 | G8: 15.96 | H8: 6.3192 | I8: -2.3 | J8: 47806.97 | K8: 45.680517
A9: 2017 | B9: 4.43 | C9: 4.0854 | D9: 10 | E9: 105.46 | F9: 8.22 | G9: 17.25 | H9: 5.8537 | I9: -4.8 | J9: 40471.48 | K9: -15.343976
A10: 2018 | B10: 6.15 | C10: 5.0781 | D10: 13.25 | E10: 121.82 | F10: 8.58 | G10: 19.04 | H10: 5.9509 | I10: -5.3 | J10: 37066.67 | K10: -8.4128626
A11: 2019 | B11: 2.5 | C11: 10.578 | D11: 7 | E11: 150.04 | F11: 9.39 | G11: 19.51 | H11: 6.934 | I11: -2.7 | J11: 40735.08 | K11: 9.8967887
A12: 2020 | B12: -1.27 | C12: 9.7401 | D12: 7 | E12: 161.84 | F12: 9.3 | G12: 17.42 | H12: 8.684 | I12: -0.2 | J12: 43755.38 | K12: 7.4144938
A13: 2021 | B13: 6.51 | C13: 9.4964 | D13: 15.75 | E13: 162.91 | F13: 9.05 | G13: 17.98 | H13: 8.9844 | I13: -3.5 | J13: 44596.07 | K13: 1.9213409
A14: 2022 | B14: 4.78 | C14: 19.8739 | D14: 22 | E14: 204.87 | F14: 10.54 | G14: 22.49 | H14: 8.0493 | I14: -3.3 | J14: 40420.45 | K14: -9.3632017
A15: 2023 | B15: -0.41 | C15: 30.7681 | D15: 13 | E15: 280.36 | F15: 10.49 | G15: 17.97 | H15: 7.8881 | I15: -0.3 | J15: 62451.04 | K15: 54.503574
A16: 2024 | B16: 3.05 | C16: 12.6325 | D16: 11 | E16: 278.58 | F16: 10.39 | G16: 17.18 | H16: 9.3963 | I16: 0.1 | J16: 115126.9 | K16: 84.34745
A17: 2025 | B17: 3.7 | C17: 3.5456 | D17: 11 | E17: 281.14 | F17: 9.99 | G17: 17.21 | H17: 9.9 | I17: -0.1 | J17: 174054.32 | K17: 51.184754

Sheet 03_Calculations
A1: Year | B1: GDP Growth (%) | C1: Inflation (%) | D1: Policy Rate EOP (%) | E1: USD/PKR Avg | F1: FX Depreciation (%) | G1: Exports (% GDP) | H1: Imports (% GDP) | I1: Trade Balance (% GDP) | J1: Remittances (% GDP) | K1: Current Account (% GDP) | L1: Real Policy Rate (Approx.) | M1: KSE-100 Return (%)
A2: 2010 | B2: ='02_Raw Data'!B2 -> 1.5 | C2: ='02_Raw Data'!C2 -> 12.9389 | D2: ='02_Raw Data'!D2 -> 0 | E2: ='02_Raw Data'!E2 -> 85.19 | G2: ='02_Raw Data'!F2 -> 12.64 | H2: ='02_Raw Data'!G2 -> 19.35 | I2: =G2-H2 -> -6.71 | J2: ='02_Raw Data'!H2 -> 4.926 | K2: ='02_Raw Data'!I2 -> -0.7 | L2: =IF(D2="","",D2-C2) -> -12.9389 | M2: ='02_Raw Data'!K2 -> 0
A3: 2011 | B3: ='02_Raw Data'!B3 -> 2.68 | C3: ='02_Raw Data'!C3 -> 11.9161 | D3: ='02_Raw Data'!D3 -> 0 | E3: ='02_Raw Data'!E3 -> 86.34 | F3: =(E3/E2-1)*100 -> 1.3499237 | G3: ='02_Raw Data'!F3 -> 13.48 | H3: ='02_Raw Data'!G3 -> 18.88 | I3: =G3-H3 -> -5.4 | J3: ='02_Raw Data'!H3 -> 5.3182 | K3: ='02_Raw Data'!I3 -> -1 | L3: =IF(D3="","",D3-C3) -> -11.9161 | M3: ='02_Raw Data'!K3 -> -5.612828
A4: 2012 | B4: ='02_Raw Data'!B4 -> 3.03 | C4: ='02_Raw Data'!C4 -> 9.6824 | D4: ='02_Raw Data'!D4 -> 0 | E4: ='02_Raw Data'!E4 -> 93.4 | F4: =(E4/E3-1)*100 -> 8.1769748 | G4: ='02_Raw Data'!F4 -> 11.87 | H4: ='02_Raw Data'!G4 -> 19.45 | I4: =G4-H4 -> -7.58 | J4: ='02_Raw Data'!H4 -> 5.6004 | K4: ='02_Raw Data'!I4 -> -0.9 | L4: =IF(D4="","",D4-C4) -> -9.6824 | M4: ='02_Raw Data'!K4 -> 48.976353
A5: 2013 | B5: ='02_Raw Data'!B5 -> 4.37 | C5: ='02_Raw Data'!C5 -> 7.6922 | D5: ='02_Raw Data'!D5 -> 0 | E5: ='02_Raw Data'!E5 -> 101.63 | F5: =(E5/E4-1)*100 -> 8.8115632 | G5: ='02_Raw Data'!F5 -> 12.18 | H5: ='02_Raw Data'!G5 -> 18.71 | I5: =G5-H5 -> -6.53 | J5: ='02_Raw Data'!H5 -> 5.6557 | K5: ='02_Raw Data'!I5 -> -1.7 | L5: =IF(D5="","",D5-C5) -> -7.6922 | M5: ='02_Raw Data'!K5 -> 49.427074
A6: 2014 | B6: ='02_Raw Data'!B6 -> 4.12 | C6: ='02_Raw Data'!C6 -> 7.1894 | D6: ='02_Raw Data'!D6 -> 6.5 | E6: ='02_Raw Data'!E6 -> 101.1 | F6: =(E6/E5-1)*100 -> -0.52149956 | G6: ='02_Raw Data'!F6 -> 11.19 | H6: ='02_Raw Data'!G6 -> 18.27 | I6: =G6-H6 -> -7.08 | J6: ='02_Raw Data'!H6 -> 6.3539 | K6: ='02_Raw Data'!I6 -> -1.3 | L6: =IF(D6="","",D6-C6) -> -0.6894 | M6: ='02_Raw Data'!K6 -> 27.196476
A7: 2015 | B7: ='02_Raw Data'!B7 -> 4.22 | C7: ='02_Raw Data'!C7 -> 2.5293 | D7: ='02_Raw Data'!D7 -> 5.75 | E7: ='02_Raw Data'!E7 -> 102.77 | F7: =(E7/E6-1)*100 -> 1.6518299 | G7: ='02_Raw Data'!F7 -> 9.97 | H7: ='02_Raw Data'!G7 -> 16.71 | I7: =G7-H7 -> -6.74 | J7: ='02_Raw Data'!H7 -> 6.4361 | K7: ='02_Raw Data'!I7 -> -0.9 | L7: =IF(D7="","",D7-C7) -> 3.2207 | M7: ='02_Raw Data'!K7 -> 2.1319723
A8: 2016 | B8: ='02_Raw Data'!B8 -> 6.57 | C8: ='02_Raw Data'!C8 -> 3.7651 | D8: ='02_Raw Data'!D8 -> 6 | E8: ='02_Raw Data'!E8 -> 104.77 | F8: =(E8/E7-1)*100 -> 1.9460932 | G8: ='02_Raw Data'!F8 -> 8.74 | H8: ='02_Raw Data'!G8 -> 15.96 | I8: =G8-H8 -> -7.22 | J8: ='02_Raw Data'!H8 -> 6.3192 | K8: ='02_Raw Data'!I8 -> -2.3 | L8: =IF(D8="","",D8-C8) -> 2.2349 | M8: ='02_Raw Data'!K8 -> 45.680517
A9: 2017 | B9: ='02_Raw Data'!B9 -> 4.43 | C9: ='02_Raw Data'!C9 -> 4.0854 | D9: ='02_Raw Data'!D9 -> 10 | E9: ='02_Raw Data'!E9 -> 105.46 | F9: =(E9/E8-1)*100 -> 0.65858547 | G9: ='02_Raw Data'!F9 -> 8.22 | H9: ='02_Raw Data'!G9 -> 17.25 | I9: =G9-H9 -> -9.03 | J9: ='02_Raw Data'!H9 -> 5.8537 | K9: ='02_Raw Data'!I9 -> -4.8 | L9: =IF(D9="","",D9-C9) -> 5.9146 | M9: ='02_Raw Data'!K9 -> -15.343976
A10: 2018 | B10: ='02_Raw Data'!B10 -> 6.15 | C10: ='02_Raw Data'!C10 -> 5.0781 | D10: ='02_Raw Data'!D10 -> 13.25 | E10: ='02_Raw Data'!E10 -> 121.82 | F10: =(E10/E9-1)*100 -> 15.512991 | G10: ='02_Raw Data'!F10 -> 8.58 | H10: ='02_Raw Data'!G10 -> 19.04 | I10: =G10-H10 -> -10.46 | J10: ='02_Raw Data'!H10 -> 5.9509 | K10: ='02_Raw Data'!I10 -> -5.3 | L10: =IF(D10="","",D10-C10) -> 8.1719 | M10: ='02_Raw Data'!K10 -> -8.4128626
A11: 2019 | B11: ='02_Raw Data'!B11 -> 2.5 | C11: ='02_Raw Data'!C11 -> 10.578 | D11: ='02_Raw Data'!D11 -> 7 | E11: ='02_Raw Data'!E11 -> 150.04 | F11: =(E11/E10-1)*100 -> 23.165326 | G11: ='02_Raw Data'!F11 -> 9.39 | H11: ='02_Raw Data'!G11 -> 19.51 | I11: =G11-H11 -> -10.12 | J11: ='02_Raw Data'!H11 -> 6.934 | K11: ='02_Raw Data'!I11 -> -2.7 | L11: =IF(D11="","",D11-C11) -> -3.578 | M11: ='02_Raw Data'!K11 -> 9.8967887
A12: 2020 | B12: ='02_Raw Data'!B12 -> -1.27 | C12: ='02_Raw Data'!C12 -> 9.7401 | D12: ='02_Raw Data'!D12 -> 7 | E12: ='02_Raw Data'!E12 -> 161.84 | F12: =(E12/E11-1)*100 -> 7.8645694 | G12: ='02_Raw Data'!F12 -> 9.3 | H12: ='02_Raw Data'!G12 -> 17.42 | I12: =G12-H12 -> -8.12 | J12: ='02_Raw Data'!H12 -> 8.684 | K12: ='02_Raw Data'!I12 -> -0.2 | L12: =IF(D12="","",D12-C12) -> -2.7401 | M12: ='02_Raw Data'!K12 -> 7.4144938
A13: 2021 | B13: ='02_Raw Data'!B13 -> 6.51 | C13: ='02_Raw Data'!C13 -> 9.4964 | D13: ='02_Raw Data'!D13 -> 15.75 | E13: ='02_Raw Data'!E13 -> 162.91 | F13: =(E13/E12-1)*100 -> 0.66114681 | G13: ='02_Raw Data'!F13 -> 9.05 | H13: ='02_Raw Data'!G13 -> 17.98 | I13: =G13-H13 -> -8.93 | J13: ='02_Raw Data'!H13 -> 8.9844 | K13: ='02_Raw Data'!I13 -> -3.5 | L13: =IF(D13="","",D13-C13) -> 6.2536 | M13: ='02_Raw Data'!K13 -> 1.9213409
A14: 2022 | B14: ='02_Raw Data'!B14 -> 4.78 | C14: ='02_Raw Data'!C14 -> 19.8739 | D14: ='02_Raw Data'!D14 -> 22 | E14: ='02_Raw Data'!E14 -> 204.87 | F14: =(E14/E13-1)*100 -> 25.756553 | G14: ='02_Raw Data'!F14 -> 10.54 | H14: ='02_Raw Data'!G14 -> 22.49 | I14: =G14-H14 -> -11.95 | J14: ='02_Raw Data'!H14 -> 8.0493 | K14: ='02_Raw Data'!I14 -> -3.3 | L14: =IF(D14="","",D14-C14) -> 2.1261 | M14: ='02_Raw Data'!K14 -> -9.3632017
... A17: 2025 | B17: ='02_Raw Data'!B17 -> 3.7 | C17: ='02_Raw Data'!C17 -> 3.5456 | D17: ='02_Raw Data'!D17 -> 11 | E17: ='02_Raw Data'!E17 -> 281.14 | F17: =(E17/E16-1)*100 -> 0.91894608 | G17: ='02_Raw Data'!F17 -> 9.99 | H17: ='02_Raw Data'!G17 -> 17.21 | I17: =G17-H17 -> -7.22 | J17: ='02_Raw Data'!H17 -> 9.9 | K17: ='02_Raw Data'!I17 -> -0.1 | L17: =IF(D17="","",D17-C17) -> 7.4544 | M17: ='02_Raw Data'!K17 -> 51.184754

Sheet 04_Correlation
A1: Correlation Matrix — Core Economic & Market Variables
A3: Variable | B3: GDP Growth | C3: Inflation | D3: Policy Rate | E3: FX Depreciation | F3: Exports % GDP | G3: Imports % GDP | H3: Trade Balance | I3: Current Account | J3: KSE Return
A4: GDP Growth | B4: =CORREL('03_Calculations'!B2:B17,'03_Calculations'!B2:B17) -> 1 | C4: =CORREL('03_Calculations'!B2:B17,'03_Calculations'!C2:C17) -> -0.532765 | D4: =CORREL('03_Calculations'!B2:B17,'03_Calculations'!D2:D17) -> 0.25256659 | E4: =CORREL('03_Calculations'!B2:B17,'03_Calculations'!F2:F17) -> -0.37626952 | F4: =CORREL('03_Calculations'!B2:B17,'03_Calculations'!G2:G17) -> -0.3110739 | G4: =CORREL('03_Calculations'!B2:B17,'03_Calculations'!H2:H17) -> -0.022727873 | H4: =CORREL('03_Calculations'!B2:B17,'03_Calculations'!I2:I17) -> -0.25931915 | I4: =CORREL('03_Calculations'!B2:B17,'03_Calculations'!K2:K17) -> -0.642386 | J4: =CORREL('03_Calculations'!B2:B17,'03_Calculations'!M2:M17) -> -0.1440025
A5: Inflation | B5: =CORREL('03_Calculations'!C2:C17,'03_Calculations'!B2:B17) -> -0.532765 | C5: =CORREL('03_Calculations'!C2:C17,'03_Calculations'!C2:C17) -> 1 | D5: =CORREL('03_Calculations'!C2:C17,'03_Calculations'!D2:D17) -> 0.30314979 | E5: =CORREL('03_Calculations'!C2:C17,'03_Calculations'!F2:F17) -> 0.77461605 | F5: =CORREL('03_Calculations'!C2:C17,'03_Calculations'!G2:G17) -> 0.28819928 | G5: =CORREL('03_Calculations'!C2:C17,'03_Calculations'!H2:H17) -> 0.4399582 | H5: =CORREL('03_Calculations'!C2:C17,'03_Calculations'!I2:I17) -> -0.13253483 | I5: =CORREL('03_Calculations'!C2:C17,'03_Calculations'!K2:K17) -> 0.24809937 | J5: =CORREL('03_Calculations'!C2:C17,'03_Calculations'!M2:M17) -> 0.16100388
A6: Policy Rate | B6: =CORREL('03_Calculations'!D2:D17,'03_Calculations'!B2:B17) -> 0.25256659 | C6: =CORREL('03_Calculations'!D2:D17,'03_Calculations'!C2:C17) -> 0.30314979 | D6: =CORREL('03_Calculations'!D2:D17,'03_Calculations'!D2:D17) -> 1 | E6: =CORREL('03_Calculations'!D2:D17,'03_Calculations'!F2:F17) -> 0.37943086 | F6: =CORREL('03_Calculations'!D2:D17,'03_Calculations'!G2:G17) -> -0.59151231 | G6: =CORREL('03_Calculations'!D2:D17,'03_Calculations'!H2:H17) -> 0.2216829 | H6: =CORREL('03_Calculations'!D2:D17,'03_Calculations'!I2:I17) -> -0.72883749 | I6: =CORREL('03_Calculations'!D2:D17,'03_Calculations'!K2:K17) -> -0.41290304 | J6: =CORREL('03_Calculations'!D2:D17,'03_Calculations'!M2:M17) -> -0.14508358
A7: FX Depreciation | B7: =CORREL('03_Calculations'!F2:F17,'03_Calculations'!B2:B17) -> -0.37626952 | C7: =CORREL('03_Calculations'!F2:F17,'03_Calculations'!C2:C17) -> 0.77461605 | D7: =CORREL('03_Calculations'!F2:F17,'03_Calculations'!D2:D17) -> 0.37943086 | E7: =CORREL('03_Calculations'!F2:F17,'03_Calculations'!F2:F17) -> 1 | F7: =CORREL('03_Calculations'!F2:F17,'03_Calculations'!G2:G17) -> -0.023094014 | G7: =CORREL('03_Calculations'!F2:F17,'03_Calculations'!H2:H17) -> 0.5505034 | H7: =CORREL('03_Calculations'!F2:F17,'03_Calculations'!I2:I17) -> -0.51099182 | I7: =CORREL('03_Calculations'!F2:F17,'03_Calculations'!K2:K17) -> -0.1033007 | J7: =CORREL('03_Calculations'!F2:F17,'03_Calculations'!M2:M17) -> -0.043704866
A8: Exports % GDP | B8: =CORREL('03_Calculations'!G2:G17,'03_Calculations'!B2:B17) -> -0.3110739 | C8: =CORREL('03_Calculations'!G2:G17,'03_Calculations'!C2:C17) -> 0.28819928 | D8: =CORREL('03_Calculations'!G2:G17,'03_Calculations'!D2:D17) -> -0.59151231 | E8: =CORREL('03_Calculations'!G2:G17,'03_Calculations'!F2:F17) -> -0.023094014 | F8: =CORREL('03_Calculations'!G2:G17,'03_Calculations'!G2:G17) -> 1 | G8: =CORREL('03_Calculations'!G2:G17,'03_Calculations'!H2:H17) -> 0.37482405 | H8: =CORREL('03_Calculations'!G2:G17,'03_Calculations'!I2:I17) -> 0.56508477 | I8: =CORREL('03_Calculations'!G2:G17,'03_Calculations'!K2:K17) -> 0.53475178 | J8: =CORREL('03_Calculations'!G2:G17,'03_Calculations'!M2:M17) -> 0.1514163
A9: Imports % GDP | B9: =CORREL('03_Calculations'!H2:H17,'03_Calculations'!B2:B17) -> -0.022727873 | C9: =CORREL('03_Calculations'!H2:H17,'03_Calculations'!C2:C17) -> 0.4399582 | D9: =CORREL('03_Calculations'!H2:H17,'03_Calculations'!D2:D17) -> 0.2216829 | E9: =CORREL('03_Calculations'!H2:H17,'03_Calculations'!F2:F17) -> 0.5505034 | F9: =CORREL('03_Calculations'!H2:H17,'03_Calculations'!G2:G17) -> 0.37482405 | G9: =CORREL('03_Calculations'!H2:H17,'03_Calculations'!H2:H17) -> 1 | H9: =CORREL('03_Calculations'!H2:H17,'03_Calculations'!I2:I17) -> -0.55307727 | I9: =CORREL('03_Calculations'!H2:H17,'03_Calculations'!K2:K17) -> -0.25230637 | J9: =CORREL('03_Calculations'!H2:H17,'03_Calculations'!M2:M17) -> -0.35258247
A10: Trade Balance | B10: =CORREL('03_Calculations'!I2:I17,'03_Calculations'!B2:B17) -> -0.25931915 | C10: =CORREL('03_Calculations'!I2:I17,'03_Calculations'!C2:C17) -> -0.13253483 | D10: =CORREL('03_Calculations'!I2:I17,'03_Calculations'!D2:D17) -> -0.72883749 | E10: =CORREL('03_Calculations'!I2:I17,'03_Calculations'!F2:F17) -> -0.51099182 | F10: =CORREL('03_Calculations'!I2:I17,'03_Calculations'!G2:G17) -> 0.56508477 | G10: =CORREL('03_Calculations'!I2:I17,'03_Calculations'!H2:H17) -> -0.55307727 | H10: =CORREL('03_Calculations'!I2:I17,'03_Calculations'!I2:I17) -> 1 | I10: =CORREL('03_Calculations'!I2:I17,'03_Calculations'!K2:K17) -> 0.7050821 | J10: =CORREL('03_Calculations'!I2:I17,'03_Calculations'!M2:M17) -> 0.44983647
A11: Current Account | B11: =CORREL('03_Calculations'!K2:K17,'03_Calculations'!B2:B17) -> -0.642386 | C11: =CORREL('03_Calculations'!K2:K17,'03_Calculations'!C2:C17) -> 0.24809937 | D11: =CORREL('03_Calculations'!K2:K17,'03_Calculations'!D2:D17) -> -0.41290304 | E11: =CORREL('03_Calculations'!K2:K17,'03_Calculations'!F2:F17) -> -0.1033007 | F11: =CORREL('03_Calculations'!K2:K17,'03_Calculations'!G2:G17) -> 0.53475178 | G11: =CORREL('03_Calculations'!K2:K17,'03_Calculations'!H2:H17) -> -0.25230637 | H11: =CORREL('03_Calculations'!K2:K17,'03_Calculations'!I2:I17) -> 0.7050821 | I11: =CORREL('03_Calculations'!K2:K17,'03_Calculations'!K2:K17) -> 1 | J11: =CORREL('03_Calculations'!K2:K17,'03_Calculations'!M2:M17) -> 0.6027272
A12: KSE Return | B12: =CORREL('03_Calculations'!M2:M17,'03_Calculations'!B2:B17) -> -0.1440025 | C12: =CORREL('03_Calculations'!M2:M17,'03_Calculations'!C2:C17) -> 0.16100388 | D12: =CORREL('03_Calculations'!M2:M17,'03_Calculations'!D2:D17) -> -0.14508358 | E12: =CORREL('03_Calculations'!M2:M17,'03_Calculations'!F2:F17) -> -0.043704866 | F12: =CORREL('03_Calculations'!M2:M17,'03_Calculations'!G2:G17) -> 0.1514163 | G12: =CORREL('03_Calculations'!M2:M17,'03_Calculations'!H2:H17) -> -0.35258247 | H12: =CORREL('03_Calculations'!M2:M17,'03_Calculations'!I2:I17) -> 0.44983647 | I12: =CORREL('03_Calculations'!M2:M17,'03_Calculations'!K2:K17) -> 0.6027272 | J12: =CORREL('03_Calculations'!M2:M17,'03_Calculations'!M2:M17) -> 1
A14: Interpretation note
A15: Correlation indicates association, not causation. Policy-rate correlations effectively use 2015–2025 because earlier years are N/A.

Sheet 05_Economic Analysis
A1: Economic Analysis — Pakistan 2010–2025
A3: Indicator | B3: 2010 | C3: 2015 | D3: 2020 | E3: 2023 | F3: 2025 | G3: 2010–2025 Change | H3: Research Use
A4: GDP Growth (%) | B4: ='02_Raw Data'!B2 -> 1.5 | C4: ='02_Raw Data'!B7 -> 4.22 | D4: ='02_Raw Data'!B12 -> -1.27 | E4: ='02_Raw Data'!B15 -> -0.41 | F4: ='02_Raw Data'!B17 -> 3.7 | G4: =F4-B4 -> 2.2 | H4: Growth-cycle analysis
A5: CPI Inflation (%) | B5: ='02_Raw Data'!C2 -> 12.9389 | C5: ='02_Raw Data'!C7 -> 2.5293 | D5: ='02_Raw Data'!C12 -> 9.7401 | E5: ='02_Raw Data'!C15 -> 30.7681 | F5: ='02_Raw Data'!C17 -> 3.5456 | G5: =F5-B5 -> -9.3933 | H5: Price-stability analysis
A6: USD/PKR Avg | B6: ='02_Raw Data'!E2 -> 85.19 | C6: ='02_Raw Data'!E7 -> 102.77 | D6: ='02_Raw Data'!E12 -> 161.84 | E6: ='02_Raw Data'!E15 -> 280.36 | F6: ='02_Raw Data'!E17 -> 281.14 | G6: =F6-B6 -> 195.95 | H6: Currency-pressure analysis
A7: Exports (% GDP) | B7: ='02_Raw Data'!F2 -> 12.64 | C7: ='02_Raw Data'!F7 -> 9.97 | D7: ='02_Raw Data'!F12 -> 9.3 | E7: ='02_Raw Data'!F15 -> 10.49 | F7: ='02_Raw Data'!F17 -> 9.99 | G7: =F7-B7 -> -2.65 | H7: External-sector openness
A8: Imports (% GDP) | B8: ='02_Raw Data'!G2 -> 19.35 | C8: ='02_Raw Data'!G7 -> 16.71 | D8: ='02_Raw Data'!G12 -> 17.42 | E8: ='02_Raw Data'!G15 -> 17.97 | F8: ='02_Raw Data'!G17 -> 17.21 | G8: =F8-B8 -> -2.14 | H8: Import dependence
A9: Remittances (% GDP) | B9: ='02_Raw Data'!H2 -> 4.926 | C9: ='02_Raw Data'!H7 -> 6.4361 | D9: ='02_Raw Data'!H12 -> 8.684 | E9: ='02_Raw Data'!H15 -> 7.8881 | F9: ='02_Raw Data'!H17 -> 9.9 | G9: =F9-B9 -> 4.974 | H9: External income support
A10: Current Account (% GDP) | B10: ='02_Raw Data'!I2 -> -0.7 | C10: ='02_Raw Data'!I7 -> -0.9 | D10: ='02_Raw Data'!I12 -> -0.2 | E10: ='02_Raw Data'!I15 -> -0.3 | F10: ='02_Raw Data'!I17 -> -0.1 | G10: =F10-B10 -> 0.6 | H10: External balance
A13: Research questions to answer
A14: 1. Which years show the clearest expansion/contraction in real GDP growth?
A15: 2. How did inflation and the policy-rate cycle move during 2018–2025?
A16: 3. How rapidly did the PKR weaken during major external-pressure periods?
A17: 4. Did external-account conditions improve when imports contracted or remittances increased?
A18: 5. How did the KSE-100 behave during major macroeconomic stress and stabilization periods?

Sheet 06_Market Analysis
A1: Market Analysis — KSE-100 and Macroeconomic Conditions
A3: Year | B3: KSE-100 Close | C3: KSE-100 Return (%) | D3: GDP Growth (%) | E3: Inflation (%) | F3: Policy Rate EOP (%) | G3: FX Depreciation (%) | H3: Current Account (% GDP)
A4: 2010 | B4: ='02_Raw Data'!J2 -> 12022.46 | C4: ='02_Raw Data'!K2 -> 0 | D4: ='02_Raw Data'!B2 -> 1.5 | E4: ='02_Raw Data'!C2 -> 12.9389 | F4: ='02_Raw Data'!D2 -> 0 | G4: ='03_Calculations'!F2 -> 0 | H4: ='02_Raw Data'!I2 -> -0.7
A5: 2011 | B5: ='02_Raw Data'!J3 -> 11347.66 | C5: ='02_Raw Data'!K3 -> -5.612828 | D5: ='02_Raw Data'!B3 -> 2.68 | E5: ='02_Raw Data'!C3 -> 11.9161 | F5: ='02_Raw Data'!D3 -> 0 | G5: ='03_Calculations'!F3 -> 1.3499237 | H5: ='02_Raw Data'!I3 -> -1
A6: 2012 | B6: ='02_Raw Data'!J4 -> 16905.33 | C6: ='02_Raw Data'!K4 -> 48.976353 | D6: ='02_Raw Data'!B4 -> 3.03 | E6: ='02_Raw Data'!C4 -> 9.6824 | F6: ='02_Raw Data'!D4 -> 0 | G6: ='03_Calculations'!F4 -> 8.1769748 | H6: ='02_Raw Data'!I4 -> -0.9
A7: 2013 | B7: ='02_Raw Data'!J5 -> 25261.14 | C7: ='02_Raw Data'!K5 -> 49.427074 | D7: ='02_Raw Data'!B5 -> 4.37 | E7: ='02_Raw Data'!C5 -> 7.6922 | F7: ='02_Raw Data'!D5 -> 0 | G7: ='03_Calculations'!F5 -> 8.8115632 | H7: ='02_Raw Data'!I5 -> -1.7
A8: 2014 | B8: ='02_Raw Data'!J6 -> 32131.28 | C8: ='02_Raw Data'!K6 -> 27.196476 | D8: ='02_Raw Data'!B6 -> 4.12 | E8: ='02_Raw Data'!C6 -> 7.1894 | F8: ='02_Raw Data'!D6 -> 6.5 | G8: ='03_Calculations'!F6 -> -0.52149956 | H8: ='02_Raw Data'!I6 -> -1.3
A9: 2015 | B9: ='02_Raw Data'!J7 -> 32816.31 | C9: ='02_Raw Data'!K7 -> 2.1319723 | D9: ='02_Raw Data'!B7 -> 4.22 | E9: ='02_Raw Data'!C7 -> 2.5293 | F9: ='02_Raw Data'!D7 -> 5.75 | G9: ='03_Calculations'!F7 -> 1.6518299 | H9: ='02_Raw Data'!I7 -> -0.9
A10: 2016 | B10: ='02_Raw Data'!J8 -> 47806.97 | C10: ='02_Raw Data'!K8 -> 45.680517 | D10: ='02_Raw Data'!B8 -> 6.57 | E10: ='02_Raw Data'!C8 -> 3.7651 | F10: ='02_Raw Data'!D8 -> 6 | G10: ='03_Calculations'!F8 -> 1.9460932 | H10: ='02_Raw Data'!I8 -> -2.3
A11: 2017 | B11: ='02_Raw Data'!J9 -> 40471.48 | C11: ='02_Raw Data'!K9 -> -15.343976 | D11: ='02_Raw Data'!B9 -> 4.43 | E11: ='02_Raw Data'!C9 -> 4.0854 | F11: ='02_Raw Data'!D9 -> 10 | G11: ='03_Calculations'!F9 -> 0.65858547 | H11: ='02_Raw Data'!I9 -> -4.8
A12: 2018 | B12: ='02_Raw Data'!J10 -> 37066.67 | C12: ='02_Raw Data'!K10 -> -8.4128626 | D12: ='02_Raw Data'!B10 -> 6.15 | E12: ='02_Raw Data'!C10 -> 5.0781 | F12: ='02_Raw Data'!D10 -> 13.25 | G12: ='03_Calculations'!F10 -> 15.512991 | H12: ='02_Raw Data'!I10 -> -5.3
A13: 2019 | B13: ='02_Raw Data'!J11 -> 40735.08 | C13: ='02_Raw Data'!K11 -> 9.8967887 | D13: ='02_Raw Data'!B11 -> 2.5 | E13: ='02_Raw Data'!C11 -> 10.578 | F13: ='02_Raw Data'!D11 -> 7 | G13: ='03_Calculations'!F11 -> 23.165326 | H13: ='02_Raw Data'!I11 -> -2.7
A14: 2020 | B14: ='02_Raw Data'!J12 -> 43755.38 | C14: ='02_Raw Data'!K12 -> 7.4144938 | D14: ='02_Raw Data'!B12 -> -1.27 | E14: ='02_Raw Data'!C12 -> 9.7401 | F14: ='02_Raw Data'!D12 -> 7 | G14: ='03_Calculations'!F12 -> 7.8645694 | H14: ='02_Raw Data'!I12 -> -0.2
A15: 2021 | B15: ='02_Raw Data'!J13 -> 44596.07 | C15: ='02_Raw Data'!K13 -> 1.9213409 | D15: ='02_Raw Data'!B13 -> 6.51 | E15: ='02_Raw Data'!C13 -> 9.4964 | F15: ='02_Raw Data'!D13 -> 15.75 | G15: ='03_Calculations'!F13 -> 0.66114681 | H15: ='02_Raw Data'!I13 -> -3.5
... A19: 2025 | B19: ='02_Raw Data'!J17 -> 174054.32 | C19: ='02_Raw Data'!K17 -> 51.184754 | D19: ='02_Raw Data'!B17 -> 3.7 | E19: ='02_Raw Data'!C17 -> 3.5456 | F19: ='02_Raw Data'!D17 -> 11 | G19: ='03_Calculations'!F17 -> 0.91894608 | H19: ='02_Raw Data'!I17 -> -0.1
A22: Market research prompts
A23: Compare KSE-100 annual returns with GDP growth and inflation without assuming direct causation.
A24: Identify years where high inflation coincided with strong or weak equity-market returns.
A25: Compare currency depreciation with KSE-100 performance and current-account conditions.
A26: Use the correlation matrix as a screening tool; explain that correlation does not establish causation.
